COPYING
GPLv2
MANIFEST.in
README.md
finalreport.md
setup.py
jupyter_kernel_singular/__init__.py
jupyter_kernel_singular/__main__.py
jupyter_kernel_singular/kernel.py
jupyter_kernel_singular.egg-info/PKG-INFO
jupyter_kernel_singular.egg-info/SOURCES.txt
jupyter_kernel_singular.egg-info/dependency_links.txt
jupyter_kernel_singular.egg-info/top_level.txt
jupyter_kernel_singular/resources/logo-32x32.png
jupyter_kernel_singular/resources/logo-64x64.png