Metadata-Version: 1.0
Name: jupyter-kernel-singular
Version: 0.9.6
Summary: A Jupyter kernel for singular
Home-page: https://github.com/sebasguts/jupyter-singular
Author: Sebastian Gutsche
Author-email: sebastian.gutsche@gmail.com
License: UNKNOWN
Platform: UNKNOWN
